mountain_tapir/__init__.py
mountain_tapir/algorithm.py
mountain_tapir/config.py
mountain_tapir/constants.py
mountain_tapir/controller.py
mountain_tapir/image_file.py
mountain_tapir/menu.py
mountain_tapir/model.py
mountain_tapir/mountain_tapir.py
mountain_tapir/open_image_dialog.py
mountain_tapir/preview.py
mountain_tapir/recent_images.py
mountain_tapir/region_maker.py
mountain_tapir/tool.py
mountain_tapir/ui_vars.py
mountain_tapir/resources/__init__.py
mountain_tapir/resources/algorithm_collage.png
mountain_tapir/resources/algorithm_frame.png
mountain_tapir/resources/algorithm_grid.png
mountain_tapir/resources/directory.png
mountain_tapir/resources/file.png
mountain_tapir/resources/refresh.png
mountain_tapir/resources/up_directory.png
mountain_tapir-1.1.2.dist-info/DESCRIPTION.rst
mountain_tapir-1.1.2.dist-info/METADATA
mountain_tapir-1.1.2.dist-info/RECORD
mountain_tapir-1.1.2.dist-info/WHEEL
mountain_tapir-1.1.2.dist-info/metadata.json
mountain_tapir-1.1.2.dist-info/top_level.txt
