Metadata-Version: 2.0
Name: mountain-tapir
Version: 1.1.2
Summary: Mountain Tapir Collage Maker is a tool for combining images into collages.
Home-page: https://github.com/tttppp/mountain_tapir
Author: tttppp
Author-email: tttppp@users.noreply.github.com
License: GPLv3+
Keywords: mountain_tapir
Platform: UNKNOWN
Classifier: Development Status :: 2 - Pre-Alpha
Classifier: Intended Audience :: Developers
Classifier: License :: OSI Approved :: GNU General Public License v3 or later (GPLv3+)
Classifier: Natural Language :: English
Classifier: Programming Language :: Python :: 2
Classifier: Programming Language :: Python :: 2.7
Classifier: Programming Language :: Python :: 3
Classifier: Programming Language :: Python :: 3.3
Classifier: Programming Language :: Python :: 3.4
Classifier: Programming Language :: Python :: 3.5
Requires-Dist: Pillow (>=4.0.0)
